Workbook

Sheet CustomerDetail
A1: S.No | B1: Transaction Date | C1: Full Name | D1: Buyer Location | E1: Buyer Date of Birth | F1: Payment Method | G1: Quantity Purchased | H1: Product Code | I1: Cost | J1: UnitPrice | K1: Revenue | L1: Profit | M1: profit Margin | N1: Sales Representative | O1: Gender
A2: 1 | B2: 45342 | C2: Allen Santos | D2: San Jose | E2: 20020 | F2: Credit Card | G2: 129 | H2: Pro04 | I2: =VLOOKUP(H2,Products!$B$8:$E$18,3,FALSE) -> 10 | J2: =VLOOKUP(H2,Products!$B$8:$E$18,4,FALSE) -> 14 | K2: =G2*J2 -> 1806 | L2: =K2 -(I2*G2) -> 516 | M2: =(L2/K2)*100 -> 28.571429 | N2: Travis Doyle | O2: Male
A3: 2 | B3: 45366 | C3: Brenda Shaw | D3: San Jose | E3: 29346 | F3: Cash | G3: 370 | H3: Pro09 | I3: =VLOOKUP(H3,Products!$B$8:$E$18,3,FALSE) -> 10 | J3: =VLOOKUP(H3,Products!$B$8:$E$18,4,FALSE) -> 45 | K3: =G3*J3 -> 16650 | L3: =K3 -(I3*G3) -> 12950 | M3: =(L3/K3)*100 -> 77.777778 | N3: Joseph Hill | O3: Female
A4: 3 | B4: 45304 | C4: Robert Hernandez | D4: San Antonio | E4: 24237 | F4: Credit Card | G4: 284 | H4: Pro02 | I4: =VLOOKUP(H4,Products!$B$8:$E$18,3,FALSE) -> 18 | J4: =VLOOKUP(H4,Products!$B$8:$E$18,4,FALSE) -> 22 | K4: =G4*J4 -> 6248 | L4: =K4 -(I4*G4) -> 1136 | M4: =(L4/K4)*100 -> 18.181818 | N4: April Watkins | O4: Other
A5: 4 | B5: 45421 | C5: Alexander Smith | D5: San Jose | E5: 16696 | F5: Debit Card | G5: 90 | H5: Pro05 | I5: =VLOOKUP(H5,Products!$B$8:$E$18,3,FALSE) -> 14 | J5: =VLOOKUP(H5,Products!$B$8:$E$18,4,FALSE) -> 28 | K5: =G5*J5 -> 2520 | L5: =K5 -(I5*G5) -> 1260 | M5: =(L5/K5)*100 -> 50 | N5: Elizabeth Guerrero | O5: Male
A6: 5 | B6: 45432 | C6: Mary Rodriguez | D6: Philadelphia | E6: 19682 | F6: Cash | G6: 475 | H6: Pro04 | I6: =VLOOKUP(H6,Products!$B$8:$E$18,3,FALSE) -> 10 | J6: =VLOOKUP(H6,Products!$B$8:$E$18,4,FALSE) -> 14 | K6: =G6*J6 -> 6650 | L6: =K6 -(I6*G6) -> 1900 | M6: =(L6/K6)*100 -> 28.571429 | N6: Tracy Lee | O6: Female
A7: 6 | B7: 45368 | C7: Clinton Haynes | D7: San Antonio | E7: 36953 | F7: Cash | G7: 346 | H7: Pro01 | I7: =VLOOKUP(H7,Products!$B$8:$E$18,3,FALSE) -> 10 | J7: =VLOOKUP(H7,Products!$B$8:$E$18,4,FALSE) -> 11 | K7: =G7*J7 -> 3806 | L7: =K7 -(I7*G7) -> 346 | M7: =(L7/K7)*100 -> 9.0909091 | N7: Sara Robertson | O7: Male
A8: 7 | B8: 45339 | C8: Jamie Steele | D8: San Diego | E8: 22039 | F8: Credit Card | G8: 366 | H8: Pro06 | I8: =VLOOKUP(H8,Products!$B$8:$E$18,3,FALSE) -> 7 | J8: =VLOOKUP(H8,Products!$B$8:$E$18,4,FALSE) -> 9 | K8: =G8*J8 -> 3294 | L8: =K8 -(I8*G8) -> 732 | M8: =(L8/K8)*100 -> 22.222222 | N8: Katie Stanton | O8: Other
A9: 8 | B9: 45441 | C9: David Hunt | D9: Chicago | E9: 17357 | F9: Cash | G9: 122 | H9: Pro01 | I9: =VLOOKUP(H9,Products!$B$8:$E$18,3,FALSE) -> 10 | J9: =VLOOKUP(H9,Products!$B$8:$E$18,4,FALSE) -> 11 | K9: =G9*J9 -> 1342 | L9: =K9 -(I9*G9) -> 122 | M9: =(L9/K9)*100 -> 9.0909091 | N9: Susan Dean | O9: Male
A10: 9 | B10: 45410 | C10: Robert Hernandez | D10: San Antonio | E10: 35670 | F10: Debit Card | G10: 299 | H10: Pro02 | I10: =VLOOKUP(H10,Products!$B$8:$E$18,3,FALSE) -> 18 | J10: =VLOOKUP(H10,Products!$B$8:$E$18,4,FALSE) -> 22 | K10: =G10*J10 -> 6578 | L10: =K10 -(I10*G10) -> 1196 | M10: =(L10/K10)*100 -> 18.181818 | N10: Travis Doyle | O10: Male
A11: 10 | B11: 45329 | C11: Alexander Smith | D11: San Jose | E11: 28393 | F11: Credit Card | G11: 327 | H11: Pro09 | I11: =VLOOKUP(H11,Products!$B$8:$E$18,3,FALSE) -> 10 | J11: =VLOOKUP(H11,Products!$B$8:$E$18,4,FALSE) -> 45 | K11: =G11*J11 -> 14715 | L11: =K11 -(I11*G11) -> 11445 | M11: =(L11/K11)*100 -> 77.777778 | N11: Joseph Hill | O11: Other
A12: 11 | B12: 45473 | C12: Mary Rodriguez | D12: Philadelphia | E12: 27423 | F12: Cash | G12: 383 | H12: Pro04 | I12: =VLOOKUP(H12,Products!$B$8:$E$18,3,FALSE) -> 10 | J12: =VLOOKUP(H12,Products!$B$8:$E$18,4,FALSE) -> 14 | K12: =G12*J12 -> 5362 | L12: =K12 -(I12*G12) -> 1532 | M12: =(L12/K12)*100 -> 28.571429 | N12: April Watkins | O12: Female
A13: 12 | B13: 45337 | C13: Samantha Wong | D13: New York | E13: 17492 | F13: Cash | G13: 468 | H13: Pro10 | I13: =VLOOKUP(H13,Products!$B$8:$E$18,3,FALSE) -> 18 | J13: =VLOOKUP(H13,Products!$B$8:$E$18,4,FALSE) -> 36 | K13: =G13*J13 -> 16848 | L13: =K13 -(I13*G13) -> 8424 | M13: =(L13/K13)*100 -> 50 | N13: April Watkins | O13: Male
... A12001: 12000 | B12001: 45647 | C12001: Crystal Brooks | D12001: Philadelphia | E12001: 34975 | F12001: Cash | G12001: 480 | H12001: Pro10 | I12001: =VLOOKUP(H12001,Products!$B$8:$E$18,3,FALSE) -> 18 | J12001: =VLOOKUP(H12001,Products!$B$8:$E$18,4,FALSE) -> 36 | K12001: =G12001*J12001 -> 17280 | L12001: =K12001 -(I12001*G12001) -> 8640 | M12001: =(L12001/K12001)*100 -> 50 | N12001: Katie Stanton | O12001: Other

Sheet Products
B8: Product Code | C8: Biscuit Brand | D8: Cost | E8: Unit Price
B9: Pro01 | C9: Butter Crunch | D9: 10 | E9: 11
B10: Pro02 | C10: Caramel Biscuits | D10: 18 | E10: 22
B11: Pro03 | C11: Choco Delight | D11: 3 | E11: 5
B12: Pro04 | C12: Cinnamon Swirls | D12: 10 | E12: 14
B13: Pro05 | C13: Ginger Snaps | D13: 14 | E13: 28
B14: Pro06 | C14: Lemon Crisps | D14: 7 | E14: 9
B15: Pro07 | C15: Oatmeal Cookies | D15: 19 | E15: 23
B16: Pro08 | C16: Peanut Butter Bites | D16: 5 | E16: 7
B17: Pro09 | C17: Shortbread | D17: 10 | E17: 45
B18: Pro10 | C18: Vanilla Wafers | D18: 18 | E18: 36
